Users/junjun/.jtconfig
jtracker/__init__.py
jtracker/cli.py
jtracker/exceptions.py
jtracker/cli/__init__.py
jtracker/cli/config.py
jtracker/cli/job.py
jtracker/cli/org.py
jtracker/cli/queue.py
jtracker/cli/user.py
jtracker/cli/workflow.py
jtracker/cli/conf/__init__.py
jtracker/cli/conf/commands.py
jtracker/cli/exec/__init__.py
jtracker/cli/exec/commands.py
jtracker/cli/job/__init__.py
jtracker/cli/job/commands.py
jtracker/cli/job/utils.py
jtracker/cli/org/__init__.py
jtracker/cli/org/commands.py
jtracker/cli/queue/__init__.py
jtracker/cli/queue/commands.py
jtracker/cli/task/__init__.py
jtracker/cli/task/commands.py
jtracker/cli/user/__init__.py
jtracker/cli/user/commands.py
jtracker/cli/wf/__init__.py
jtracker/cli/wf/commands.py
jtracker/client/__init__.py
jtracker/client/config.py
jtracker/client/job.py
jtracker/client/org.py
jtracker/client/queue.py
jtracker/client/user.py
jtracker/client/workflow.py
jtracker/core/__init__.py
jtracker/core/job.py
jtracker/core/workflow.py
jtracker/etcdb/__init__.py
jtracker/execution/__init__.py
jtracker/execution/executor.py
jtracker/execution/worker.py
jtracker/execution/scheduler/__init__.py
jtracker/execution/scheduler/base.py
jtracker/execution/scheduler/jess.py
jtracker/execution/scheduler/local.py
jtracker-0.2.0a34.dist-info/LICENSE
jtracker-0.2.0a34.dist-info/METADATA
jtracker-0.2.0a34.dist-info/WHEEL
jtracker-0.2.0a34.dist-info/entry_points.txt
jtracker-0.2.0a34.dist-info/top_level.txt
jtracker-0.2.0a34.dist-info/RECORD
