Metadata-Version: 2.1
Name: jtracker
Version: 0.2.0a34
Summary: Command line client for JTracker
Home-page: https://github.com/jtracker-io/jt-cli
Author: Junjun Zhang
Author-email: junjun.ca@gmail.com
License: Apache License, Version 2.0
Platform: UNKNOWN
Classifier: Development Status :: 3 - Alpha
Classifier: License :: OSI Approved :: Apache Software License
Classifier: Operating System :: OS Independent
Requires-Python: >=3
Requires-Dist: click (>=6.1)
Requires-Dist: retrying (>=1.3.3)
Requires-Dist: PyYAML (>=3.10)
Requires-Dist: requests (>=2.20.0)
Requires-Dist: click-log
